django_jwt/__init__.py
django_jwt/apps.py
django_jwt/auth.py
django_jwt/exceptions.py
django_jwt/middleware.py
django_jwt/openid.py
django_jwt/patterns.py
django_jwt/rest_framework.py
django_jwt/settings_utils.py
django_jwt/urls.py
django_jwt/view_utils.py
django_jwt/views.py
django_jwt/migrations/__init__.py
django_jwt/server/__init__.py
django_jwt/server/admin.py
django_jwt/server/apps.py
django_jwt/server/forms.py
django_jwt/server/models.py
django_jwt/server/serializers.py
django_jwt/server/signals.py
django_jwt/server/urls.py
django_jwt/server/views.py
django_jwt/server/views_utils.py
django_jwt/server/migrations/0001_initial.py
django_jwt/server/migrations/0002_webpage_logout_all.py
django_jwt/server/migrations/0003_nonceused_privateclaimswebpage_restrictuserstoweb_and_more.py
django_jwt/server/migrations/__init__.py
django_jwt/server/templates/django_jwt/oidc_confirmation.html
django_jwt/templates/django_jwt/fake_login.html
django_jwt_oidc-1.0.12.dist-info/LICENSE.md
django_jwt_oidc-1.0.12.dist-info/METADATA
django_jwt_oidc-1.0.12.dist-info/WHEEL
django_jwt_oidc-1.0.12.dist-info/top_level.txt
django_jwt_oidc-1.0.12.dist-info/RECORD
