Metadata-Version: 2.1
Name: django-jwt-oidc
Version: 1.0.12
Summary: Django library that implements the authentification for OpenId SSO with JWT from oauth2.
Home-page: https://github.com/Casassarnau/django-jwt
Author: Arnau Casas Saez
Author-email: casassarnau@gmail.com
License: MIT
Project-URL: Bug Tracker, https://github.com/Casassarnau/django-jwt/issues
Classifier: Programming Language :: Python :: 3
Classifier: License :: OSI Approved :: MIT License
Classifier: Operating System :: OS Independent
Requires-Python: >=3.6
License-File: LICENSE.md
Requires-Dist: django >=2.2
Requires-Dist: pycryptodome
Requires-Dist: jwcrypto
Requires-Dist: urllib3
